{
  "name": "乐天·运用型优惠券效果",
  "description": "运用型优惠券（优惠券进阶广告）效果报表；使用当前标签页登录态调用 API。",
  "auth": {
    "type": "xsrf",
    "hint": "需先在当前浏览器标签页登录 RMS（ad.rms.rakuten.co.jp）；请求会携带 Cookie 并从 Cookie 注入 X-XSRF-TOKEN",
    "show_hint": false
  },
  "navigate_url": "https://ad.rms.rakuten.co.jp/cpnadv/performance_reports",
  "mode": "fetch",
  "url": "https://ad.rms.rakuten.co.jp/cpnadv/performance_reports/retrieve",
  "method": "POST",
  "headers": {
    "Accept": "application/json",
    "Accept-Language": "ja",
    "Content-Type": "application/x-www-form-urlencoded; charset=UTF-8"
  },
  "xsrf_cookie": "XSRF-TOKEN",
  "vars": {
    "start_date": {
      "type": "str",
      "required": true,
      "description": "开始日 (YYYY-MM-DD)",
      "example": "2026-03-01"
    },
    "end_date": {
      "type": "str",
      "required": true,
      "description": "结束日 (YYYY-MM-DD)",
      "example": "2026-03-29"
    },
    "page": {
      "type": "int",
      "default": 0,
      "description": "页码（从 0 起）"
    }
  },
  "body": "selectionType=1&periodType=2&searchStartDate={{start_date}}&searchEndDate={{end_date}}&templateDiv=101&displayStatuses=true,true,true,true,true,true,true,true,true,true,true,true,true,true,true,true,true,true,true,true,true,true,true,true,true,true,true,true,true,true,true,true,true,true,true,true,true,true,true,true,true,true,true,true,true,true,true,true,true,true,true,true,true,true,true,true,true,true,true,true,true,true,true,true,true,true,true,true,true,true,true,true,true,true,true,true,true,true,true,true,true,true,true,true,true,true,true,true,true,true,true,true,true,true,true,true,true,true,true,true,true,true,true,true,true,true,true,true,true,true,true,true,true,true,true,true,true,true,true,true,true,true,true,true,true,true,true,true,true,true,true,true,true,true,true,true,true,true,true,true,true,true,true,true,true,true,true,true,true,true,true,true,true,true,true,true,true,true,true,true,true,true,true,true,true,true,true,true,true,true,true,true,true,true,true,true,true,true,true,true,true,true,true,true,true,true,true,true,true,true,true,true,true,true,true,true,true,true,true,true,true,true,true,true,true,true,true,true,true,true,true,true,true,true,true,true,true,true,true,true,true,true,true,true,true,true,true,true,true,true,true,true,true,true&page={{page}}"
}
